simplesystray/__init__.py
simplesystray/traybar.py
simplesystray/win32_adapter.py
simplesystray-0.1.0.dist-info/LICENSE
simplesystray-0.1.0.dist-info/METADATA
simplesystray-0.1.0.dist-info/WHEEL
simplesystray-0.1.0.dist-info/top_level.txt
simplesystray-0.1.0.dist-info/RECORD
