Metadata-Version: 2.1
Name: simplesystray
Version: 0.1.0
Summary: Adds support for a simple icon on the system tray, clone of infi-systray but maintained
Home-page: https://github.com/actorpus/systrayv2
Author: actorpus (alex)
Author-email: alex@actorpus.com
Project-URL: Bug Tracker, https://github.com/actorpus/systrayv2/issues
Classifier: Programming Language :: Python :: 3
Classifier: Operating System :: Microsoft
Requires-Python: >=3.7
License-File: LICENSE
